setup.py
bibgen/__init__.py
bibgen/rst.py
bibgen/xml.py
bibgen.egg-info/PKG-INFO
bibgen.egg-info/SOURCES.txt
bibgen.egg-info/dependency_links.txt
bibgen.egg-info/requires.txt
bibgen.egg-info/top_level.txt
bibgen/citeproc/__init__.py
bibgen/citeproc/bibtexparser.py
bibgen/citeproc/mendeley.py
bibgen/formatter/__init__.py
bibgen/formatter/docbook.py
bibgen/formatter/rst.py
bin/bibgen